llama_index/llms/lmstudio/__init__.py
llama_index/llms/lmstudio/base.py
llama_index_llms_lmstudio-0.4.1.dist-info/METADATA
llama_index_llms_lmstudio-0.4.1.dist-info/WHEEL
llama_index_llms_lmstudio-0.4.1.dist-info/licenses/LICENSE
llama_index_llms_lmstudio-0.4.1.dist-info/RECORD
