Metadata-Version: 2.4
Name: llama-index-llms-lmstudio
Version: 0.4.1
Summary: llama-index llms lmstudio integration
Author-email: Shivam Kalra <dev@kaltq.com>
License-Expression: MIT
License-File: LICENSE
Requires-Python: <4.0,>=3.9
Requires-Dist: llama-index-core<0.15,>=0.13.0
